pyproptree/__init__.py
pyproptree/io.py
pyproptree-2.0.0.dist-info/LICENSE
pyproptree-2.0.0.dist-info/METADATA
pyproptree-2.0.0.dist-info/WHEEL
pyproptree-2.0.0.dist-info/top_level.txt
pyproptree-2.0.0.dist-info/RECORD
