Metadata-Version: 2.1
Name: pyproptree
Version: 2.0.0
Summary: A lightweight property tree == node implementation for Python
Home-page: UNKNOWN
Author: UNKNOWN
Author-email: UNKNOWN
License: UNKNOWN
Platform: UNKNOWN
Requires-Dist: typing
Requires-Dist: plum-dispatch
Requires-Dist: lxml
